<service-view-mappings>
	<service-view-mapping service-id="additionWithXml" path="/fouroperate/result.page" type="forward"></service-view-mapping>
	<service-view-mapping service-id="subtractWithXml" path="/fouroperate/result.page" type="forward"></service-view-mapping>
	<service-view-mapping service-id="multiWithXml" path="/fouroperate/result.page" type="forward"></service-view-mapping>
	<service-view-mapping service-id="divisionWithXml" path="/fouroperate/result.page" type="forward"></service-view-mapping>
	<service-view-mapping service-id="additionWithAnno" path="/fouroperate/result.page" type="forward"></service-view-mapping>
	<service-view-mapping service-id="subtractWithAnno" path="/fouroperate/result.page" type="forward"></service-view-mapping>
	<service-view-mapping service-id="multiWithAnno" path="/fouroperate/result.page" type="forward"></service-view-mapping>
	<service-view-mapping service-id="divisionWithAnno" path="/fouroperate/result.page" type="forward"></service-view-mapping>
</service-view-mappings>